{
  "$schema": "https://json-schema.org/draft/2020-12/schema",
  "$id": "https://axme.dev/schemas/public_api/api.billing.plan.update.request.v1.json",
  "title": "ApiBillingPlanUpdateRequestV1",
  "type": "object",
  "additionalProperties": false,
  "required": [
    "org_id",
    "workspace_id",
    "plan_code",
    "currency",
    "billing_cycle",
    "monthly_commit_minor",
    "overage_unit_price_minor",
    "updated_by_actor_id"
  ],
  "properties": {
    "org_id": {
      "type": "string",
      "format": "uuid"
    },
    "workspace_id": {
      "type": "string",
      "format": "uuid"
    },
    "plan_code": {
      "type": "string",
      "minLength": 2,
      "maxLength": 64
    },
    "currency": {
      "type": "string",
      "minLength": 3,
      "maxLength": 16
    },
    "billing_cycle": {
      "type": "string",
      "enum": [
        "monthly",
        "annual"
      ]
    },
    "monthly_commit_minor": {
      "type": "integer",
      "minimum": 0
    },
    "seats_included": {
      "type": "integer",
      "minimum": 0
    },
    "overage_unit_price_minor": {
      "type": "integer",
      "minimum": 0
    },
    "updated_by_actor_id": {
      "type": "string",
      "minLength": 1,
      "maxLength": 255
    },
    "metadata": {
      "type": "object"
    }
  }
}
